langchain_snowflake/__init__.py
langchain_snowflake/_connection/__init__.py
langchain_snowflake/_connection/auth_utils.py
langchain_snowflake/_connection/base.py
langchain_snowflake/_connection/session_manager.py
langchain_snowflake/_error_handling.py
langchain_snowflake/chat_models/__init__.py
langchain_snowflake/chat_models/auth.py
langchain_snowflake/chat_models/base.py
langchain_snowflake/chat_models/streaming.py
langchain_snowflake/chat_models/structured_output.py
langchain_snowflake/chat_models/tools.py
langchain_snowflake/chat_models/utils.py
langchain_snowflake/formatters.py
langchain_snowflake/py.typed
langchain_snowflake/retrievers.py
langchain_snowflake/tools/__init__.py
langchain_snowflake/tools/_base.py
langchain_snowflake/tools/analyst.py
langchain_snowflake/tools/cortex_functions.py
langchain_snowflake/tools/query.py
langchain_snowflake-0.2.1.dist-info/LICENSE
langchain_snowflake-0.2.1.dist-info/METADATA
langchain_snowflake-0.2.1.dist-info/WHEEL
langchain_snowflake-0.2.1.dist-info/RECORD
