Metadata-Version: 2.1
Name: langchain-snowflake
Version: 0.2.1
Summary: An integration package connecting Snowflake and LangChain
Home-page: https://github.com/langchain-ai/langchain-snowflake
License: MIT
Requires-Python: >=3.9,<3.12
Classifier: License :: OSI Approved :: MIT License
Classifier: Programming Language :: Python :: 3
Classifier: Programming Language :: Python :: 3.9
Classifier: Programming Language :: Python :: 3.10
Classifier: Programming Language :: Python :: 3.11
Provides-Extra: key-pair
Requires-Dist: aiohttp (>=3.9.0,<4.0.0)
Requires-Dist: cryptography (>=42.0.0,<43.0.0) ; extra == "key-pair"
Requires-Dist: langchain (>=0.3.27,<0.4.0)
Requires-Dist: langchain-core (>=0.3.75,<0.4.0)
Requires-Dist: langgraph (>=0.6.4,<0.7.0)
Requires-Dist: langgraph-prebuilt (>=0.6.4,<0.7.0)
Requires-Dist: langsmith (>=0.4.21,<0.5.0)
Requires-Dist: pydantic (>=2.7.0,<3.0.0)
Requires-Dist: snowflake (>=0.8.0,<1.0)
Requires-Dist: snowflake-snowpark-python (>=1.20.0,<2.0.0)
Project-URL: Repository, https://github.com/langchain-ai/langchain-snowflake
Project-URL: Release Notes, https://github.com/langchain-ai/langchain-snowflake/releases
Project-URL: Source Code, https://github.com/langchain-ai/langchain-snowflake/tree/main/libs/snowflake
